score_models/__init__.py
score_models/base.py
score_models/definitions.py
score_models/dsm.py
score_models/kernel_slic.py
score_models/score_model.py
score_models/slic.py
score_models/sliced_score_matching.py
score_models/utils.py
score_models/architectures/__init__.py
score_models/architectures/ddpm.py
score_models/architectures/mlp.py
score_models/architectures/ncsnpp.py
score_models/layers/__init__.py
score_models/layers/attention_block.py
score_models/layers/combine.py
score_models/layers/conditional_batchnorm2d.py
score_models/layers/conditional_instancenorm2d.py
score_models/layers/conditional_instancenorm2d_plus.py
score_models/layers/conv1dsame.py
score_models/layers/conv2dsame.py
score_models/layers/conv3dsame.py
score_models/layers/conv_layers.py
score_models/layers/ddpm_resnet_block.py
score_models/layers/downsample.py
score_models/layers/ncsn_resnet_block.py
score_models/layers/projection_embedding.py
score_models/layers/resnet_block_biggan.py
score_models/layers/spectral_normalization.py
score_models/layers/squeeze_and_excitation.py
score_models/layers/style_gan_conv.py
score_models/layers/up_or_downsampling.py
score_models/layers/up_or_downsampling1d.py
score_models/layers/up_or_downsampling2d.py
score_models/layers/up_or_downsampling3d.py
score_models/layers/upfirdn1d.py
score_models/layers/upfirdn2d.py
score_models/layers/upfirdn3d.py
score_models/layers/upsample.py
score_models/ode/__init__.py
score_models/ode/euler.py
score_models/ode/heun.py
score_models/ode/runge_kutta.py
score_models/sde/__init__.py
score_models/sde/sde.py
score_models/sde/tsvesde.py
score_models/sde/vesde.py
score_models/sde/vpsde.py
score_models-0.5.11.dist-info/LICENSE.txt
score_models-0.5.11.dist-info/METADATA
score_models-0.5.11.dist-info/WHEEL
score_models-0.5.11.dist-info/top_level.txt
score_models-0.5.11.dist-info/RECORD
