Metadata-Version: 2.1
Name: score-models
Version: 0.5.11
Summary: A simple pytorch interface for score model and basic diffusion.
Home-page: https://github.com/AlexandreAdam/torch_score_models
Author: Alexandre Adam
Author-email: alexandre.adam@umontreal.ca
License: UNKNOWN
Platform: UNKNOWN
Classifier: Development Status :: 3 - Alpha
Classifier: Intended Audience :: Developers
Classifier: License :: OSI Approved :: MIT License
Classifier: Programming Language :: Python :: 3.8
Requires-Python: >=3.8
Requires-Dist: torch (>=2.0)
Requires-Dist: scipy
Requires-Dist: torch-ema
Requires-Dist: h5py
Requires-Dist: numpy
Requires-Dist: tqdm
